{
  "event_id": "41577ab8-3570-46f7-9a1f-d3311e6368c8",
  "source_id": "11905fb1-e66f-4640-a547-2d48eed21616",
  "set": "Readings and Discussion Featuring UAlberta Writer in Residence Ifeoma Chinwuba and Edmonton Poet Laureate Titilope Sonuga 03-04-2022 16:28 [Index]",
  "annotations": [
    {
      "start_time": 0,
      "end_time": 0,
      "annotation": [
        {
          "text": "Introduction - Michael O'Driscoll"
        }
      ],
      "tags": [],
      "uuid": "b86c752e-6cd7-4577-a608-1acdb909d6cd"
    },
    {
      "start_time": 0,
      "end_time": 0,
      "annotation": [
        {
          "text": "Host, Dr. Uche Peter Umezurike"
        }
      ],
      "tags": [],
      "uuid": "0962793a-6bf7-485b-ae6d-f2aa56476c62"
    },
    {
      "start_time": 0,
      "end_time": 0,
      "annotation": [
        {
          "text": "Welcome, introduction and brief bios of the guest writers."
        }
      ],
      "tags": [],
      "uuid": "de7c7d17-dee8-4f60-b517-d09ec2e565df"
    },
    {
      "start_time": 0,
      "end_time": 0,
      "annotation": [
        {
          "text": "Titilope Sonuga reads the poem Interrogators of Orchids by Maggie Smith"
        }
      ],
      "tags": [],
      "uuid": "5d1b0a45-2052-44d9-8f03-27554b898be8"
    },
    {
      "start_time": 0,
      "end_time": 0,
      "annotation": [
        {
          "text": "Ifeoma Chinwuba reads the poem The Solitary Reaper by William Wordsworth"
        }
      ],
      "tags": [],
      "uuid": "ed459e66-f895-48e5-84d7-62791e964040"
    },
    {
      "start_time": 0,
      "end_time": 0,
      "annotation": [
        {
          "text": "William Wordsworth\nThe Solitary Reaper\nLines Written a Few Miles above Tintern Abbey\nOde: Intimations of Immorality from Recollections of Early Childhood"
        }
      ],
      "tags": [],
      "uuid": "cce55425-abd0-4074-9d23-ff569b88ea13"
    },
    {
      "start_time": 0,
      "end_time": 0,
      "annotation": [
        {
          "text": "Titilope Sonuga on literary influences"
        }
      ],
      "tags": [],
      "uuid": "6dae5e46-dad7-4d33-a195-395fecf449c2"
    },
    {
      "start_time": 0,
      "end_time": 0,
      "annotation": [
        {
          "text": "Maggie Smith\nMabel Segun\nBuche Emecheta\nToni Morrison\nSonia Sanchez\nMaya Angelou"
        }
      ],
      "tags": [],
      "uuid": "860bdf3c-39a9-422d-bba4-939f94836582"
    },
    {
      "start_time": 0,
      "end_time": 0,
      "annotation": [
        {
          "text": "Ifeoma Chinwuba on literary influences"
        }
      ],
      "tags": [],
      "uuid": "664bd98b-0e92-4201-bfd0-12c7203fb5cd"
    },
    {
      "start_time": 0,
      "end_time": 0,
      "annotation": [
        {
          "text": "Ifeoma Chinwuba reads an excerpt from African Romance"
        }
      ],
      "tags": [],
      "uuid": "28755a48-54ee-4963-ac7a-520d80ad383b"
    },
    {
      "start_time": 0,
      "end_time": 0,
      "annotation": [
        {
          "text": "Titilope Sonuga reads the poem Missing"
        }
      ],
      "tags": [],
      "uuid": "0339c1db-e877-41ea-9e17-7b73bf8f3535"
    },
    {
      "start_time": 0,
      "end_time": 0,
      "annotation": [
        {
          "text": "Titilope Sonuga reads the poem Missing from the collection This Is How We Disappear"
        }
      ],
      "tags": [],
      "uuid": "e9392a87-4089-4404-90d5-28e2f3c694ba"
    },
    {
      "start_time": 0,
      "end_time": 0,
      "annotation": [
        {
          "text": "Titilope Sonuga on how literature can incite conversation"
        }
      ],
      "tags": [],
      "uuid": "084f159e-e446-4bbc-a191-833aa02a555a"
    },
    {
      "start_time": 0,
      "end_time": 0,
      "annotation": [
        {
          "text": "Question from the Host: How can we get literature to incite more conversation and awareness about the commodification of women?"
        }
      ],
      "tags": [],
      "uuid": "f3807706-06be-4989-909b-f6fe8eb1a422"
    },
    {
      "start_time": 0,
      "end_time": 0,
      "annotation": [
        {
          "text": "Ifeoma Chinwuba on how literature can incite conversation"
        }
      ],
      "tags": [],
      "uuid": "2e522820-284b-4c8f-9819-c1c251430ac5"
    },
    {
      "start_time": 0,
      "end_time": 0,
      "annotation": [
        {
          "text": "Question from the Host: How can we get literature to incite more conversation and awareness about the commodification of women?"
        }
      ],
      "tags": [],
      "uuid": "8a95c15d-1076-4f5f-a263-775bcae872ff"
    },
    {
      "start_time": 0,
      "end_time": 0,
      "annotation": [
        {
          "text": "Titilope Sonuga reads an untitled poem"
        }
      ],
      "tags": [],
      "uuid": "8803223c-32ca-4a0d-b154-f05d37f9c814"
    },
    {
      "start_time": 0,
      "end_time": 0,
      "annotation": [
        {
          "text": "Ifeoma Chinwuba reads an excerpt from Waiting for Maria"
        }
      ],
      "tags": [],
      "uuid": "af732658-5b5c-4980-b910-4b508090c5b8"
    },
    {
      "start_time": 0,
      "end_time": 0,
      "annotation": [
        {
          "text": "Questions from event registrants"
        }
      ],
      "tags": [],
      "uuid": "b9dee079-ecd0-4628-826a-eb5a4f5ab2eb"
    },
    {
      "start_time": 0,
      "end_time": 0,
      "annotation": [
        {
          "text": "Host, Dr. Uche Peter Umezurike, invites questions from event registrants."
        }
      ],
      "tags": [],
      "uuid": "dece1eba-d46d-4d03-8df8-d42c47f60288"
    },
    {
      "start_time": 0,
      "end_time": 0,
      "annotation": [
        {
          "text": "Closing"
        }
      ],
      "tags": [],
      "uuid": "f85b2001-4b16-450f-9c9c-cc1fb3ffa9c1"
    },
    {
      "start_time": 0,
      "end_time": 0,
      "annotation": [
        {
          "text": "Closing:  Host, Uchechukwu Peter Umezurike, thanks the guests and Michael O'Driscoll makes closing remarks."
        }
      ],
      "tags": [],
      "uuid": "99a27b3a-2c92-41cd-b28a-66d314776473"
    }
  ]
}